libdebug/__init__.py
libdebug/libdebug.py
libdebug/liblog.py
libdebug/py.typed
libdebug/architectures/__init__.py
libdebug/architectures/breakpoint_validator.py
libdebug/architectures/call_utilities_manager.py
libdebug/architectures/call_utilities_provider.py
libdebug/architectures/ptrace_software_breakpoint_patcher.py
libdebug/architectures/register_helper.py
libdebug/architectures/stack_unwinding_manager.py
libdebug/architectures/stack_unwinding_provider.py
libdebug/architectures/syscall_hijacker.py
libdebug/architectures/thread_context_helper.py
libdebug/architectures/aarch64/__init__.py
libdebug/architectures/aarch64/aarch64_breakpoint_validator.py
libdebug/architectures/aarch64/aarch64_call_utilities.py
libdebug/architectures/aarch64/aarch64_ptrace_register_holder.py
libdebug/architectures/aarch64/aarch64_registers.py
libdebug/architectures/aarch64/aarch64_stack_unwinder.py
libdebug/architectures/aarch64/aarch64_thread_context.py
libdebug/architectures/amd64/__init__.py
libdebug/architectures/amd64/amd64_breakpoint_validator.py
libdebug/architectures/amd64/amd64_call_utilities.py
libdebug/architectures/amd64/amd64_ptrace_register_holder.py
libdebug/architectures/amd64/amd64_registers.py
libdebug/architectures/amd64/amd64_stack_unwinder.py
libdebug/architectures/amd64/amd64_thread_context.py
libdebug/architectures/amd64/compat/__init__.py
libdebug/architectures/amd64/compat/i386_over_amd64_ptrace_register_holder.py
libdebug/architectures/amd64/compat/i386_over_amd64_registers.py
libdebug/architectures/amd64/compat/i386_over_amd64_thread_context.py
libdebug/architectures/i386/__init__.py
libdebug/architectures/i386/i386_breakpoint_validator.py
libdebug/architectures/i386/i386_call_utilities.py
libdebug/architectures/i386/i386_ptrace_register_holder.py
libdebug/architectures/i386/i386_registers.py
libdebug/architectures/i386/i386_stack_unwinder.py
libdebug/architectures/i386/i386_thread_context.py
libdebug-0.9.0.dist-info/METADATA
libdebug-0.9.0.dist-info/WHEEL
libdebug-0.9.0.dist-info/RECORD
libdebug-0.9.0.dist-info/licenses/LICENSE
