Metadata-Version: 2.1
Name: libdebug
Version: 0.9.0
Summary: A Python library for the debugging of binary executables.
Keywords: libdebug,debugger,elf,ptrace,gdb,debug,ctf,reverse-engineering,reverse,rev,scriptable,script
Author: JinBlack, Io-no, MrIndeciso, Frank01001
License: MIT License
Classifier: Development Status :: 3 - Alpha
Classifier: Environment :: Console
Classifier: Intended Audience :: Developers
Classifier: Intended Audience :: Science/Research
Classifier: Intended Audience :: Information Technology
Classifier: Intended Audience :: System Administrators
Classifier: License :: OSI Approved :: MIT License
Classifier: Natural Language :: English
Classifier: Operating System :: POSIX :: Linux
Classifier: Programming Language :: C
Classifier: Programming Language :: Python :: 3
Classifier: Programming Language :: Python :: 3 :: Only
Classifier: Programming Language :: Python :: 3.10
Classifier: Programming Language :: Python :: 3.11
Classifier: Programming Language :: Python :: 3.12
Classifier: Programming Language :: Python :: 3.13
Classifier: Topic :: Security
Classifier: Topic :: Software Development :: Debuggers
Classifier: Typing :: Typed
Project-URL: homepage, https://libdebug.org
Project-URL: repository, https://github.com/libdebug/libdebug/
Project-URL: issues, https://github.com/libdebug/libdebug/issues
Requires-Python: >=3.10
Requires-Dist: psutil
Requires-Dist: pyelftools
Requires-Dist: prompt-toolkit
Requires-Dist: requests
Provides-Extra: dev
Requires-Dist: rich; extra == "dev"
